prompthub/__init__.py
prompthub/errors.py
prompthub/hub.py
prompthub-0.1.17.dist-info/METADATA
prompthub-0.1.17.dist-info/WHEEL
prompthub-0.1.17.dist-info/top_level.txt
prompthub-0.1.17.dist-info/RECORD
