Metadata-Version: 2.1
Name: prompthub
Version: 0.1.17
Summary: Prompt Hub SDK.
Home-page: https://github.com/DataMini/PromptHub
Author: lele
Requires-Dist: jinja2
